z3c/objpath/README.rst
z3c/objpath/__init__.py
z3c/objpath/interfaces.py
z3c/objpath/path.py
z3c/objpath/tests.py
z3c_objpath-3.0.dist-info/LICENSE.rst
z3c_objpath-3.0.dist-info/METADATA
z3c_objpath-3.0.dist-info/WHEEL
z3c_objpath-3.0.dist-info/top_level.txt
z3c_objpath-3.0.dist-info/RECORD
