Metadata-Version: 2.2
Name: z3c.objpath
Version: 3.0
Summary: Generate and resolve paths to to objects.
Home-page: https://github.com/zopefoundation/z3c.objpath
Author: Martijn Faassen
Author-email: faassen@startifact.com
License: ZPL
Keywords: Zope
Classifier: Programming Language :: Python :: 3
Classifier: Programming Language :: Python :: 3.9
Classifier: Programming Language :: Python :: 3.10
Classifier: Programming Language :: Python :: 3.11
Classifier: Programming Language :: Python :: 3.12
Classifier: Programming Language :: Python :: 3.13
Classifier: Programming Language :: Python :: Implementation :: CPython
Classifier: Programming Language :: Python :: Implementation :: PyPy
Classifier: License :: OSI Approved :: Zope Public License
Requires-Python: >=3.9
License-File: LICENSE.rst
Requires-Dist: setuptools
Requires-Dist: zope.interface
Dynamic: author
Dynamic: author-email
Dynamic: classifier
Dynamic: description
Dynamic: home-page
Dynamic: keywords
Dynamic: license
Dynamic: requires-dist
Dynamic: requires-python
Dynamic: summary
